MANIFEST.in
setup.cfg
setup.py
stratus_api/storage/__init__.py
stratus_api/storage/gcs.py
stratus_api/storage/s3.py
stratus_api/storage/sftp.py
stratus_api/storage/utilities.py
stratus_api_storage.egg-info/PKG-INFO
stratus_api_storage.egg-info/SOURCES.txt
stratus_api_storage.egg-info/dependency_links.txt
stratus_api_storage.egg-info/requires.txt
stratus_api_storage.egg-info/top_level.txt