Metadata-Version: 2.1
Name: stratus-api-storage
Version: 0.0.6
Summary: An API framework for simplified development
Home-page: https://github.com/dot-at-adara/storage
Author: DOT
Author-email: dot@adara.com
Classifier: Programming Language :: Python :: 3
Classifier: License :: OSI Approved :: MIT License
Classifier: Operating System :: OS Independent
Requires-Python: >=3.11
